odoo/addons/stock_reception_screen/README.rst
odoo/addons/stock_reception_screen/__init__.py
odoo/addons/stock_reception_screen/__manifest__.py
odoo/addons/stock_reception_screen/i18n/es_AR.po
odoo/addons/stock_reception_screen/i18n/stock_reception_screen.pot
odoo/addons/stock_reception_screen/models/__init__.py
odoo/addons/stock_reception_screen/models/manual_barcode.py
odoo/addons/stock_reception_screen/models/product_packaging.py
odoo/addons/stock_reception_screen/models/stock_move.py
odoo/addons/stock_reception_screen/models/stock_move_line.py
odoo/addons/stock_reception_screen/models/stock_picking.py
odoo/addons/stock_reception_screen/models/stock_reception_screen.py
odoo/addons/stock_reception_screen/readme/CONTRIBUTORS.rst
odoo/addons/stock_reception_screen/readme/DESCRIPTION.rst
odoo/addons/stock_reception_screen/security/ir.model.access.csv
odoo/addons/stock_reception_screen/static/description/icon.png
odoo/addons/stock_reception_screen/static/description/index.html
odoo/addons/stock_reception_screen/static/src/js/autofocus.js
odoo/addons/stock_reception_screen/static/src/scss/screen.scss
odoo/addons/stock_reception_screen/tests/__init__.py
odoo/addons/stock_reception_screen/tests/test_reception_screen.py
odoo/addons/stock_reception_screen/views/assets.xml
odoo/addons/stock_reception_screen/views/manual_barcode.xml
odoo/addons/stock_reception_screen/views/stock_move_line.xml
odoo/addons/stock_reception_screen/views/stock_picking.xml
odoo/addons/stock_reception_screen/views/stock_reception_screen.xml
odoo13_addon_stock_reception_screen-13.0.1.6.2.dist-info/METADATA
odoo13_addon_stock_reception_screen-13.0.1.6.2.dist-info/WHEEL
odoo13_addon_stock_reception_screen-13.0.1.6.2.dist-info/top_level.txt
odoo13_addon_stock_reception_screen-13.0.1.6.2.dist-info/RECORD
