Metadata-Version: 2.1
Name: odoo13-addon-stock-reception-screen
Version: 13.0.1.6.2
Summary: Dedicated screen to receive/scan goods.
Home-page: https://github.com/OCA/wms
Author: Camptocamp, Odoo Community Association (OCA)
Author-email: support@odoo-community.org
License: AGPL-3
Platform: UNKNOWN
Classifier: Programming Language :: Python
Classifier: Framework :: Odoo
Classifier: License :: OSI Approved :: GNU Affero General Public License v3
Classifier: Development Status :: 3 - Alpha
Requires-Python: >=3.5
Requires-Dist: odoo13-addon-product-packaging-dimension
Requires-Dist: odoo13-addon-product-packaging-type-pallet
Requires-Dist: odoo13-addon-stock-quant-package-dimension
Requires-Dist: odoo13-addon-stock-storage-type
Requires-Dist: odoo (<13.1dev,>=13.0a)
